setup.py
suryazi_distributions/Binomialdistribution.py
suryazi_distributions/Gaussiandistribution.py
suryazi_distributions/Generaldistribution.py
suryazi_distributions/__init__.py
suryazi_distributions.egg-info/PKG-INFO
suryazi_distributions.egg-info/SOURCES.txt
suryazi_distributions.egg-info/dependency_links.txt
suryazi_distributions.egg-info/not-zip-safe
suryazi_distributions.egg-info/top_level.txt